[{"STATE_UT":"ANDHRA PRADESH","TOTAL_IPC_CRIMES":189780},{"STATE_UT":"ARUNACHAL PRADESH","TOTAL_IPC_CRIMES":2286},{"STATE_UT":"ASSAM","TOTAL_IPC_CRIMES":66714},{"STATE_UT":"BIHAR","TOTAL_IPC_CRIMES":135896},{"STATE_UT":"CHHATTISGARH","TOTAL_IPC_CRIMES":57218},{"STATE_UT":"GOA","TOTAL_IPC_CRIMES":3449},{"STATE_UT":"GUJARAT","TOTAL_IPC_CRIMES":123371},{"STATE_UT":"HARYANA","TOTAL_IPC_CRIMES":60741},{"STATE_UT":"HIMACHAL PRADESH","TOTAL_IPC_CRIMES":14312},{"STATE_UT":"JAMMU & KASHMIR","TOTAL_IPC_CRIMES":24504},{"STATE_UT":"JHARKHAND","TOTAL_IPC_CRIMES":35838},{"STATE_UT":"KARNATAKA","TOTAL_IPC_CRIMES":137600},{"STATE_UT":"KERALA","TOTAL_IPC_CRIMES":172137},{"STATE_UT":"MADHYA PRADESH","TOTAL_IPC_CRIMES":217094},{"STATE_UT":"MAHARASHTRA","TOTAL_IPC_CRIMES":204902},{"STATE_UT":"MANIPUR","TOTAL_IPC_CRIMES":3218},{"STATE_UT":"MEGHALAYA","TOTAL_IPC_CRIMES":2755},{"STATE_UT":"MIZORAM","TOTAL_IPC_CRIMES":1821},{"STATE_UT":"NAGALAND","TOTAL_IPC_CRIMES":1083},{"STATE_UT":"ODISHA","TOTAL_IPC_CRIMES":61277},{"STATE_UT":"PUNJAB","TOTAL_IPC_CRIMES":34883},{"STATE_UT":"RAJASTHAN","TOTAL_IPC_CRIMES":165622},{"STATE_UT":"SIKKIM","TOTAL_IPC_CRIMES":596},{"STATE_UT":"TAMIL NADU","TOTAL_IPC_CRIMES":192879},{"STATE_UT":"TRIPURA","TOTAL_IPC_CRIMES":5803},{"STATE_UT":"UTTAR PRADESH","TOTAL_IPC_CRIMES":195135},{"STATE_UT":"UTTARAKHAND","TOTAL_IPC_CRIMES":8774},{"STATE_UT":"WEST BENGAL","TOTAL_IPC_CRIMES":143197},{"STATE_UT":"A & N ISLANDS","TOTAL_IPC_CRIMES":793},{"STATE_UT":"CHANDIGARH","TOTAL_IPC_CRIMES":3542},{"STATE_UT":"D & N HAVELI","TOTAL_IPC_CRIMES":372},{"STATE_UT":"DAMAN & DIU","TOTAL_IPC_CRIMES":224},{"STATE_UT":"LAKSHADWEEP","TOTAL_IPC_CRIMES":44},{"STATE_UT":"PUDUCHERRY","TOTAL_IPC_CRIMES":4362}]